greek_stemmer/__init__.py
greek_stemmer/__version__.py
greek_stemmer/stemmer.py
greek_stemmer/closets/POS.py
greek_stemmer/closets/__init__.py
greek_stemmer/closets/rules.py
greek_stemmer/closets/word_exceptions.py
greek_stemmer/lemmatizers/__init__.py
greek_stemmer/lemmatizers/non_verb.py
greek_stemmer/lemmatizers/verb.py
greek_stemmer/tools/__init__.py
greek_stemmer/tools/general_tools.py
greek_stemmer/tools/text_tools.py
greek_stemmer_pos-1.1.2.dist-info/AUTHORS.rst
greek_stemmer_pos-1.1.2.dist-info/LICENSE
greek_stemmer_pos-1.1.2.dist-info/METADATA
greek_stemmer_pos-1.1.2.dist-info/WHEEL
greek_stemmer_pos-1.1.2.dist-info/top_level.txt
greek_stemmer_pos-1.1.2.dist-info/RECORD
