Metadata-Version: 2.1
Name: greek-stemmer-pos
Version: 1.1.2
Summary: A greek stemmer that utilizes Part of Speech (PoS) tags
Home-page: https://github.com/kpech21/Greek-Stemmer
Author: Konstantinos Pechlivanis
Author-email: kpechlivanis21@gmail.com
License: GNU License
Platform: UNKNOWN
Classifier: Natural Language :: English
Classifier: Natural Language :: Greek
Classifier: Intended Audience :: Developers
Classifier: Intended Audience :: Education
Classifier: License :: OSI Approved :: GNU General Public License v3 (GPLv3)
Classifier: Programming Language :: Python
Classifier: Programming Language :: Python :: 3 :: Only
Classifier: Programming Language :: Python :: 3.6
Classifier: Programming Language :: Python :: 3.7
Classifier: Programming Language :: Python :: 3.8
Classifier: Programming Language :: Python :: 3.9
Requires-Python: >=3.6
License-File: LICENSE
License-File: AUTHORS.rst
Requires-Dist: pytest
Requires-Dist: pytest-cov
